{
  "cast_type": "instant",
  "cooldown": 0,
  "cost": {},
  "duration": 0,
  "max_targets": 1,
  "name": "Ambush (Assassin)",
  "next_chain": [],
  "previous_chain": [],
  "range": 6,
  "sources": [{
    "id": "ambush-assassin",
    "data_type": "talent"
  }],
  "tags": [
    "Assassin",
    "Cutthroat",
    "Exposed"
  ],
  "targeting": "reticle",
  "type": "melee attack",
  "description": "Steps you from the shadows to deliver a lethal surprise attack causing 181-272 + 227% Weapon Damage and generating two Pips. This attack gains a 100% Critical Hit Chance and generates an additional Pip when used against exposed targets."
}
