{
  "cast_type": "hold channeled",
  "cooldown": 23,
  "cost": {
    "name": "resource",
    "cost": 16
  },
  "duration": 10,
  "max_targets": 5,
  "name": "Ghost Army",
  "next_chain": [],
  "previous_chain": [],
  "range": 0,
  "sources": [{
    "id": "banshee",
    "data_type": "discipline"
  }],
  "tags": [],
  "targeting": "rectangle",
  "type": "ranged attack",
  "description": "Calls forth a Ghost Army in front of you dealing 60-81 + 70% Weapon Damage and healing for your 12.5% of the Damage dealt after 15 seconds."
}
