{
  "cast_type": "instant",
  "cooldown": 9,
  "cost": {
    "name": "resource",
    "cost": 18
  },
  "duration": 0,
  "max_targets": 5,
  "name": "Ricochet Shot (Sharpshooter)",
  "next_chain": [],
  "previous_chain": [],
  "range": 15,
  "sources": [{
    "id": "sharpshooter",
    "data_type": "discipline"
  }],
  "tags": [
    "AoE"
  ],
  "targeting": "reticle",
  "type": "ranged attack",
  "description": "Fires an arrow that can ricochet to strike up to four additional nearby enemies for 65-89 + 77% Weapon Damage and has a 100% Critical Hit Chance after the second ricochet."
}
