{
  "cast_type": "instant",
  "cooldown": 0,
  "cost": {
    "name": "dodge",
    "cost": 1
  },
  "duration": 0,
  "max_targets": 1,
  "name": "Zealot Rush",
  "next_chain": [],
  "previous_chain": [],
  "range": 20,
  "sources": [{
    "id": "nethari",
    "data_type": "discipline"
  }],
  "tags": [
    "Dodge",
    "Nethari"
  ],
  "targeting": "self",
  "type": "dodge",
  "description": "Dash quickly moving 20m in your WASD direction at the cost of one Dodge pip. You recover one Dodge pip every 20 seconds."
}
